{
  "collectionName": "components_page_components_homes",
  "info": {
    "displayName": "Home",
    "icon": "house",
    "description": ""
  },
  "options": {},
  "attributes": {
    "intro": {
      "type": "string"
    },
    "title": {
      "type": "text"
    },
    "subtitle": {
      "type": "text"
    },
    "typedText": {
      "type": "customField",
      "options": {
        "output": "HTML",
        "preset": "rich"
      },
      "customField": "plugin::ckeditor.CKEditor"
    }
  }
}
